sparse_pe.v
`timescale 1ns / 1ps

module sparse_pe (
    input wire clk,
    input wire rst_n,
    
    // Inputs
    input wire [15:0] packed_activations, // Four 4-bit inputs packed together
    input wire [3:0]  mask,               // The sparsity mask (e.g., 1001)
    input wire [7:0]  weight_top,         // First kept weight
    input wire [7:0]  weight_bot,         // Second kept weight
    
    // Output
    output reg [31:0] result
);

    // 1. Unpack Activations
    wire [3:0] act [0:3];
    assign act[0] = packed_activations[3:0];
    assign act[1] = packed_activations[7:4];
    assign act[2] = packed_activations[11:8];
    assign act[3] = packed_activations[15:12];

    // 2. Decode Mask (Priority Encoder)
    // Determine which activation index matches the kept weights
    reg [1:0] idx_top;
    reg [1:0] idx_bot;
    
    always @(*) begin
        // Default
        idx_top = 0; idx_bot = 0;
        
        case (mask)
            4'b0011: begin idx_top = 1; idx_bot = 0; end
            4'b0101: begin idx_top = 2; idx_bot = 0; end
            4'b1001: begin idx_top = 3; idx_bot = 0; end
            4'b0110: begin idx_top = 2; idx_bot = 1; end
            4'b1010: begin idx_top = 3; idx_bot = 1; end
            4'b1100: begin idx_top = 3; idx_bot = 2; end
            default: begin idx_top = 0; idx_bot = 0; end
        endcase
    end

    // 3. MUX Selection
    reg [3:0] operand_a_top;
    reg [3:0] operand_a_bot;
    
    always @(*) begin
        operand_a_top = act[idx_top];
        operand_a_bot = act[idx_bot];
    end

    // 4. Multiply and Accumulate
    always @(posedge clk or negedge rst_n) begin
        if (!rst_n) begin
            result <= 0;
        end else begin
            result <= (weight_top * operand_a_top) + (weight_bot * operand_a_bot);
        end
    end

endmodule

tb_sparse_pe.v
`timescale 1ns / 1ps

module tb_sparse_pe;

    // Signals
    reg clk, rst_n;
    reg [15:0] packed_activations;
    reg [3:0]  mask;
    reg [7:0]  weight_top, weight_bot;
    wire [31:0] result;

    // --- UPDATED ARRAY SIZES ---
    reg [15:0] mem_act [0:9999];       // Size 10,000
    reg [7:0]  mem_weights [0:19999];  // Size 20,000 (2 per test)
    reg [3:0]  mem_mask [0:9999];      // Size 10,000
    reg [15:0] mem_expected [0:9999];  // Size 10,000

    // Instantiate Design
    sparse_pe uut (
        .clk(clk), 
        .rst_n(rst_n), 
        .packed_activations(packed_activations), 
        .mask(mask), 
        .weight_top(weight_top), 
        .weight_bot(weight_bot), 
        .result(result)
    );

    // Clock Gen (100 MHz)
    always #5 clk = ~clk;

    integer i;
    reg [15:0] expected_val;

    initial begin
        // Init
        clk = 0; rst_n = 0;
        
        // VCD Dump for Waveforms
        $dumpfile("waves.vcd");
        $dumpvars(0, tb_sparse_pe);
        
        // Load Hex Files
        $readmemh("activations.hex", mem_act);
        $readmemh("weights.hex", mem_weights);
        $readmemh("mask.hex", mem_mask);
        $readmemh("expected.hex", mem_expected);

        // Reset
        #20 rst_n = 1;
        
        // --- UPDATED LOOP LIMIT ---
        for (i = 0; i < 10000; i = i + 1) begin
            // Drive Inputs
            packed_activations = mem_act[i];
            mask = mem_mask[i];
            
            // Weights logic (Stride of 2)
            weight_top = mem_weights[2*i];
            weight_bot = mem_weights[(2*i)+1];

            // Wait for processing
            @(posedge clk); #1; 

            // Check Output
            expected_val = mem_expected[i];
            @(posedge clk); #1;
            
            if (result !== expected_val) begin
                $display("Test %0d: FAIL (Out: %0d, Exp: %0d)", i, result, expected_val);
                $stop;
            end
            
            // Optional: Print status every 1000 tests so you know it's alive
            if (i % 1000 == 0) begin
                 $display("Test %0d passed...", i);
            end
        end

        $display("-------------------------------");
        $display("ALL 10,000 TESTS PASSED!.");
        $display("-------------------------------");
        $finish;
    end

endmodule

waves.vcd
$date
	Sat Nov 29 22:36:50 2025
$end
$version
	Icarus Verilog
$end
$timescale
	1ps
$end
$scope module tb_sparse_pe $end
$var wire 32 ! result [31:0] $end
$var reg 1 " clk $end
$var reg 16 # expected_val [15:0] $end
$var reg 4 $ mask [3:0] $end
$var reg 16 % packed_activations [15:0] $end
$var reg 1 & rst_n $end
$var reg 8 ' weight_bot [7:0] $end
$var reg 8 ( weight_top [7:0] $end
$var integer 32 ) i [31:0] $end
$scope module uut $end
$var wire 1 " clk $end
$var wire 4 * mask [3:0] $end
$var wire 16 + packed_activations [15:0] $end
$var wire 1 & rst_n $end
$var wire 8 , weight_bot [7:0] $end
$var wire 8 - weight_top [7:0] $end
$var reg 2 . idx_bot [1:0] $end
$var reg 2 / idx_top [1:0] $end
$var reg 4 0 operand_a_bot [3:0] $end
$var reg 4 1 operand_a_top [3:0] $end
$var reg 32 2 result [31:0] $end
$upscope $end
$upscope $end
$enddefinitions $end
$comment Show the parameter values. $end
$dumpall
$end
#0
$dumpvars
b0 2
bx 1
bx 0
bx /
bx .
bx -
bx ,
bx +
bx *
bx )
bx (
bx '
0&
bx %
bx $
bx #
0"
b0 !
$end
#5000
1"
#10000
0"
#15000
1"
#20000
b11 0
b0 1
b0 .
b1 /
0"
b111 '
b111 ,
b100 (
b100 -
b11 $
b11 *
b111100000000011 %
b111100000000011 +
b0 )
1&
#25000
b10101 !
b10101 2
1"
#26000
b10101 #
#30000
0"
#35000
1"
#36000
b1101 0
b1 1
b110 '
b110 ,
b111 (
b111 -
b10000000011101 %
b10000000011101 +
b1 )
#40000
0"
#45000
b1010101 !
b1010101 2
1"
#46000
b1010101 #
#50000
0"
#55000
1"
#56000
b1110 0
b1000 1
b10 .
b11 /
b1101 '
b1101 ,
b1010 (
b1010 -
b1100 $
b1100 *
b1000111001111101 %
b1000111001111101 +
b10 )
#60000
0"
#65000
b100000110 !
b100000110 2
1"
#66000
b100000110 #
#70000
0"
#75000
1"
#76000
b1000 0
b110 1
b0 .
b10 /
b11 '
b11 ,
b1100 (
b1100 -
b101 $
b101 *
b1010011001001000 %
b1010011001001000 +
b11 )
#80000
0"
#85000
b1100000 !
b1100000 2
1"
#86000
b1100000 #
#90000
0"
#95000
1"
#96000
b1011 0
b1000 1
b1110 '
b1110 ,
b1100010111011 %
b1100010111011 +
b100 )
#100000
0"
#105000
b11111010 !
b11111010 2
1"
#106000
b11111010 #
#110000
0"
#115000
1"
#116000
b110 1
b1 .
b10 /
b111 '
b111 ,
b1001 (
b1001 -
b110 $
b110 *
b10011010111001 %
b10011010111001 +
b101 )
#120000
0"
#125000
b10000011 !
b10000011 2
1"
#126000
b10000011 #
#130000
0"
#135000
1"
#136000
b111 0
b11 1
b0 .
b1 /
b1110 '
b1110 ,
b1011 (
b1011 -
b11 $
b11 *
b1000110000110111 %
b1000110000110111 +
b110 )
#140000
0"
#145000
1"
#150000
0"
#155000
1"
#156000
b110 0
b10 1
b1 .
b11 /
b111 '
b111 ,
b1110 (
b1110 -
b1010 $
b1010 *
b10100001101011 %
b10100001101011 +
b111 )
#160000
0"
#165000
b1000110 !
b1000110 2
1"
#166000
b1000110 #
#170000
0"
#175000
1"
#176000
b1000 0
b1010 1
b1010 (
b1010 -
b1010011110001100 %
b1010011110001100 +
b1000 )
#180000
0"
#185000
b10011100 !
b10011100 2
1"
#186000
b10011100 #
#190000
0"
#195000
1"
#196000
b10 0
b110 1
b10 .
b11 /
b1111 '
b1111 ,
b1100 (
b1100 -
b1100 $
b1100 *
b110001010001100 %
b110001010001100 +
b1001 )
#200000
0"
#205000
b1100110 !
b1100110 2
1"
#206000
b1100110 #
#210000
0"
#215000
1"
#216000
b1000 0
b100 1
b1101 '
b1101 ,
b100100001001110 %
b100100001001110 +
b1010 )
#220000
0"
#225000
b10011000 !
b10011000 2
1"
#226000
b10011000 #
#230000
0"
#235000
1"
#236000
b100 0
b1111 1
b11 '
b11 ,
b100 (
b100 -
b1111010001111011 %
b1111010001111011 +
b1011 )
#240000
0"
#245000
b1001000 !
b1001000 2
1"
#246000
b1001000 #
#250000
0"
#255000
1"
#256000
b101 0
b1101 1
b0 .
b1 /
b1100 '
b1100 ,
b1110 (
b1110 -
b11 $
b11 *
b1100001011010101 %
b1100001011010101 +
b1100 )
#260000
0"
#265000
b11110010 !
b11110010 2
1"
#266000
b11110010 #
#270000
0"
#275000
1"
#276000
b1000 0
b11 1
b1 .
b11 /
b1101 '
b1101 ,
b1010 $
b1010 *
b11101010000011 %
b11101010000011 +
b1101 )
#280000
0"
#285000
b10010010 !
b10010010 2
1"
#286000
b10010010 #
#290000
0"
#295000
1"
#296000
b0 0
b0 .
b11 /
b1001 '
b1001 ,
b1011 (
b1011 -
b1001 $
b1001 *
b11010110000000 %
b11010110000000 +
b1110 )
#300000
0"
#305000
b100001 !
b100001 2
1"
#306000
b100001 #
#310000
0"
#315000
1"
#316000
b1010 0
b1111 1
b10 .
b11 /
b1011 '
b1011 ,
b1001 (
b1001 -
b1100 $
b1100 *
b1111101000000101 %
b1111101000000101 +
b1111 )
#320000
0"
#325000
b11110101 !
b11110101 2
1"
#326000
b11110101 #
#330000
0"
#335000
1"
#336000
b1 0
b10 1
b1 .
b11 /
b1111 '
b1111 ,
b100 (
b100 -
b1010 $
b1010 *
b10011100010111 %
b10011100010111 +
b10000 )
#340000
0"
#345000
b10111 !
b10111 2
1"
#346000
b10111 #
#350000
0"
#355000
1"
#356000
b100 0
b1000 1
b0 .
b11 /
b1101 '
b1101 ,
b1001 (
b1001 -
b1001 $
b1001 *
b1000010111110100 %
b1000010111110100 +
b10001 )
#360000
0"
#365000
b1111100 !
b1111100 2
1"
#366000
b1111100 #
#370000
0"
#375000
1"
#376000
b1011 0
b1110 1
b1 .
b10 /
b111 '
b111 ,
b111 (
b111 -
b110 $
b110 *
b1110111010111100 %
b1110111010111100 +
b10010 )
#380000
0"
#385000
b10101111 !
b10101111 2
1"
#386000
b10101111 #
#390000
0"
#395000
1"
#396000
b0 0
b111 1
b1 .
b11 /
b10 '
b10 ,
b1010 $
b1010 *
b111011100001010 %
b111011100001010 +
b10011 )
#400000
0"
#405000
b110001 !
b110001 2
1"
#406000
b110001 #
#410000
0"
#415000
1"
#416000
b1 0
b1010 1
b1 .
b10 /
b1000 '
b1000 ,
b1111 (
b1111 -
b110 $
b110 *
b10101000010010 %
b10101000010010 +
b10100 )
#420000
0"
#425000
b10011110 !
b10011110 2
1"
#426000
b10011110 #
#430000
0"
#435000
1"
#436000
b100 0
b1111 1
b0 .
b1 /
b1101 '
b1101 ,
b110 (
b110 -
b11 $
b11 *
b1111011111110100 %
b1111011111110100 +
b10101 )
#440000
0"
#445000
b10001110 !
b10001110 2
1"
#446000
b10001110 #
#450000
0"
#455000
1"
#456000
b1101 0
b1101 1
b10 /
b1110 '
b1110 ,
b11 (
b11 -
b101 $
b101 *
b1101110110111101 %
b1101110110111101 +
b10110 )
#460000
0"
#465000
b11011101 !
b11011101 2
1"
#466000
b11011101 #
#470000
0"
#475000
1"
#476000
b1100 0
b11 1
b110 '
b110 ,
b1110 (
b1110 -
b111001110101100 %
b111001110101100 +
b10111 )
#480000
0"
#485000
b1110010 !
b1110010 2
1"
#486000
b1110010 #
#490000
0"
#495000
1"
#496000
b1101 0
b1000 1
b111 '
b111 ,
b1110100001011101 %
b1110100001011101 +
b11000 )
#500000
0"
#505000
b11001011 !
b11001011 2
1"
#506000
b11001011 #
#510000
0"
#515000
1"
#516000
b10 0
b111 1
b10 .
b11 /
b1111 '
b1111 ,
b1111 (
b1111 -
b1100 $
b1100 *
b111001000000001 %
b111001000000001 +
b11001 )
#520000
0"
#525000
b10000111 !
b10000111 2
1"
#526000
b10000111 #
#530000
0"
#535000
1"
#536000
b110 0
b1 1
b0 .
b10 /
b1100 '
b1100 ,
b1100 (
b1100 -
b101 $
b101 *
b101000111000110 %
b101000111000110 +
b11010 )
#540000
0"
#545000
b1010100 !
b1010100 2
1"
#546000
b1010100 #
#550000
0"
#555000
1"
#556000
b1001 0
b1101 1
b1 .
b10 /
b110 '
b110 ,
b1001 (
b1001 -
b110 $
b110 *
b1111110110011110 %
b1111110110011110 +
b11011 )
#560000
0"
#565000
b10101011 !
b10101011 2
1"
#566000
b10101011 #
#570000
0"
#575000
1"
#576000
b1 0
b1010 1
b1111 '
b1111 ,
b101 (
b101 -
b1101000010001 %
b1101000010001 +
b11100 )
#580000
0"
#585000
b1000001 !
b1000001 2
1"
#586000
b1000001 #
#590000
0"
#595000
1"
#596000
b10 0
b101 1
b0 .
b1 /
b111 '
b111 ,
b1100 (
b1100 -
b11 $
b11 *
b10001001010010 %
b10001001010010 +
b11101 )
#600000
0"
#605000
b1001010 !
b1001010 2
1"
#606000
b1001010 #
#610000
0"
#615000
1"
#616000
b1 0
b1101 1
b10 /
b1000 '
b1000 ,
b1010 (
b1010 -
b101 $
b101 *
b1010110100100001 %
b1010110100100001 +
b11110 )
#620000
0"
#625000
b10001010 !
b10001010 2
1"
#626000
b10001010 #
#630000
0"
#635000
1"
#636000
b1000 0
b1100 1
b1 /
b1110 '
b1110 ,
b11 $
b11 *
b1001010011001000 %
b1001010011001000 +
b11111 )
#640000
0"
#645000
b11101000 !
b11101000 2
1"
#646000
b11101000 #
#650000
0"
#655000
1"
#656000
b1110 0
b10 1
b10 /
b1000 '
b1000 ,
b1011 (
b1011 -
b101 $
b101 *
b110001000111110 %
b110001000111110 +
b100000 )
#660000
0"
#665000
b10000110 !
b10000110 2
1"
#666000
b10000110 #
#670000
0"
#675000
1"
#676000
b111 0
b1011 1
b1 /
b1110 '
b1110 ,
b1001 (
b1001 -
b11 $
b11 *
b101100110110111 %
b101100110110111 +
b100001 )
#680000
0"
#685000
b11000101 !
b11000101 2
1"
#686000
b11000101 #
#690000
0"
#695000
1"
#696000
b1000 0
b11 1
b10 .
b11 /
b1000 '
b1000 ,
b1100 $
b1100 *
b11100001000011 %
b11100001000011 +
b100010 )
#700000
0"
#705000
b1011011 !
b1011011 2
1"
#706000
b1011011 #
#710000
0"
#715000
1"
#716000
b110 0
b1010 1
b0 .
b1 /
b1111 '
b1111 ,
b1000 (
b1000 -
b11 $
b11 *
b1000011010100110 %
b1000011010100110 +
b100011 )
#720000
0"
#725000
b10101010 !
b10101010 2
1"
#726000
b10101010 #
#730000
0"
#735000
1"
#736000
b1101 0
b1 1
b10 /
b1010 '
b1010 ,
b101 $
b101 *
b110001101 %
b110001101 +
b100100 )
#740000
0"
#745000
b10001010 !
b10001010 2
1"
#746000
b10001010 #
#750000
0"
#755000
1"
#756000
b11 1
b1 .
b11 /
b100 '
b100 ,
b1011 (
b1011 -
b1010 $
b1010 *
b11000011011110 %
b11000011011110 +
b100101 )
#760000
0"
#765000
b1010101 !
b1010101 2
1"
#766000
b1010101 #
#770000
0"
#775000
1"
#776000
b1 1
b1011 '
b1011 ,
b1010011010100 %
b1010011010100 +
b100110 )
#780000
0"
#785000
b10011010 !
b10011010 2
1"
#786000
b10011010 #
#790000
0"
#795000
1"
#796000
b110 0
b11 1
b0 .
b10 /
b1101 '
b1101 ,
b111 (
b111 -
b101 $
b101 *
b1011001101110110 %
b1011001101110110 +
b100111 )
#800000
0"
#805000
b1100011 !
b1100011 2
1"
#806000
b1100011 #
#810000
0"
#815000
1"
#816000
b101 0
b1101 1
b1 /
b1010 '
b1010 ,
b1101 (
b1101 -
b11 $
b11 *
b101000011010101 %
b101000011010101 +
b101000 )
#820000
0"
#825000
b11011011 !
b11011011 2
1"
#826000
b11011011 #
#830000
0"
#835000
1"
#836000
b1 1
b11 /
b1111 '
b1111 ,
b1110 (
b1110 -
b1001 $
b1001 *
b1110000110101 %
b1110000110101 +
b101001 )
#840000
0"
#845000
b1011001 !
b1011001 2
1"
#846000
b1011001 #
#850000
0"
#855000
1"
#856000
b111 0
b111 1
b10 .
b11 /
b1100 '
b1100 ,
b1010 (
b1010 -
b1100 $
b1100 *
b111011110011011 %
b111011110011011 +
b101010 )
#860000
0"
#865000
b10011010 !
b10011010 2
1"
#866000
b10011010 #
#870000
0"
#875000
1"
#876000
b1000 0
b10 1
b0 .
b1 /
b11 $
b11 *
b1011100000101000 %
b1011100000101000 +
b101011 )
#880000
0"
#885000
b1110100 !
b1110100 2
1"
#886000
b1110100 #
#890000
0"
#895000
1"
#896000
b101 0
b1000 1
b1 .
b10 /
b1101 '
b1101 ,
b1011 (
b1011 -
b110 $
b110 *
b1100001011000 %
b1100001011000 +
b101100 )
#900000
0"
#905000
b10011001 !
b10011001 2
1"
#906000
b10011001 #
#910000
0"
#915000
1"
#916000
b1101 0
b1100 1
b0 .
b10 /
b1000 '
b1000 ,
b1101 (
b1101 -
b101 $
b101 *
b110110000111101 %
b110110000111101 +
b101101 )
#920000
0"
#925000
b100000100 !
b100000100 2
1"
#926000
b100000100 #
#930000
0"
#935000
1"
#936000
b110 0
b1011 1
b1 /
b1010 '
b1010 ,
b1010 (
b1010 -
b11 $
b11 *
b10110110110110 %
b10110110110110 +
b101110 )
#940000
0"
#945000
b10101010 !
b10101010 2
1"
#946000
b10101010 #
#950000
0"
#955000
1"
#956000
b1001 0
b1100 1
b11 /
b1001 '
b1001 ,
b1101 (
b1101 -
b1001 $
b1001 *
b1100101011011001 %
b1100101011011001 +
b101111 )
#960000
0"
#965000
b11101101 !
b11101101 2
1"
#966000
b11101101 #
#970000
0"
#975000
1"
#976000
b101 0
b1001 1
b1 .
b10 /
b1001 (
b1001 -
b110 $
b110 *
b1100100101011100 %
b1100100101011100 +
b110000 )
#980000
0"
#985000
b1111110 !
b1111110 2
1"
#986000
b1111110 #
#990000
0"
#995000
1"
#996000
b1101 0
b1110 1
b0 .
b10 /
b1110 '
b1110 ,
b1111 (
b1111 -
b101 $
b101 *
b1110111010101101 %
b1110111010101101 +
b110001 )
#1000000
0"
#1005000
b110001000 !
b110001000 2
1"
#1006000
b110001000 #
#1010000
0"
#1015000
1"
#1016000
b10 0
b1001 1
b1 /
b111 '
b111 ,
b1001 (
b1001 -
b11 $
b11 *
b10101010010010 %
b10101010010010 +
b110010 )
#1020000
0"
#1025000
b1011111 !
b1011111 2
1"
#1026000
b1011111 #
#1030000
0"
#1035000
1"
#1036000
b100 0
b1 1
b10 /
b1111 '
b1111 ,
b1110 (
b1110 -
b101 $
b101 *
b111000100000100 %
b111000100000100 +
b110011 )
#1040000
0"
#1045000
b1001010 !
b1001010 2
1"
#1046000
b1001010 #
#1050000
0"
#1055000
1"
#1056000
b110 0
b1100 1
b1 /
b111 '
b111 ,
b100 (
b100 -
b11 $
b11 *
b1100111111000110 %
b1100111111000110 +
b110100 )
#1060000
0"
#1065000
b1011010 !
b1011010 2
1"
#1066000
b1011010 #
#1070000
0"
#1075000
1"
#1076000
b111 0
b1110 1
b1 .
b11 /
b1110 (
b1110 -
b1010 $
b1010 *
b1110010101111101 %
b1110010101111101 +
b110101 )
#1080000
0"
#1085000
b11110101 !
b11110101 2
1"
#1086000
b11110101 #
#1090000
0"
#1095000
1"
#1096000
b1110 0
b1110 '
b1110 ,
b1111 (
b1111 -
b1110101011100100 %
b1110101011100100 +
b110110 )
#1100000
0"
#1105000
b110010110 !
b110010110 2
1"
#1106000
b110010110 #
#1110000
0"
#1115000
1"
#1116000
b1000 1
b0 .
b11 /
b1111 '
b1111 ,
b1110 (
b1110 -
b1001 $
b1001 *
b1000011110001110 %
b1000011110001110 +
b110111 )
#1120000
0"
#1125000
b101000010 !
b101000010 2
1"
#1126000
b101000010 #
#1130000
0"
#1135000
1"
#1136000
b10 0
b1001 1
b1 /
b1010 '
b1010 ,
b1010 (
b1010 -
b11 $
b11 *
b1000011110010010 %
b1000011110010010 +
b111000 )
#1140000
0"
#1145000
b1101110 !
b1101110 2
1"
#1146000
b1101110 #
#1150000
0"
#1155000
1"
#1156000
b1100 0
b100 1
b10 .
b11 /
b1101 '
b1101 ,
b1101 (
b1101 -
b1100 $
b1100 *
b100110001110100 %
b100110001110100 +
b111001 )
#1160000
0"
#1165000
b11010000 !
b11010000 2
1"
#1166000
b11010000 #
#1170000
0"
#1175000
1"
#1176000
b1110 0
b1101 1
b1 .
b10 /
b1100 (
b1100 -
b110 $
b110 *
b1110111101010 %
b1110111101010 +
b111010 )
#1180000
0"
#1185000
b101010010 !
b101010010 2
1"
#1186000
b101010010 #
#1190000
0"
#1195000
1"
#1196000
b1111 0
b0 1
b1100 '
b1100 ,
b1101 (
b1101 -
b1011000011111100 %
b1011000011111100 +
b111011 )
#1200000
0"
#1205000
b10110100 !
b10110100 2
1"
#1206000
b10110100 #
#1210000
0"
#1215000
1"
#1216000
b1000 1
b0 .
b10 /
b1111 '
b1111 ,
b1100 (
b1100 -
b101 $
b101 *
b1101100001111111 %
b1101100001111111 +
b111100 )
#1220000
0"
#1225000
b101000001 !
b101000001 2
1"
#1226000
b101000001 #
#1230000
0"
#1235000
1"
#1236000
b101 0
b100 1
b1 .
b11 /
b1100 '
b1100 ,
b10 (
b10 -
b1010 $
b1010 *
b100111001011100 %
b100111001011100 +
b111101 )
#1240000
0"
#1245000
b1000100 !
b1000100 2
1"
#1246000
b1000100 #
#1250000
0"
#1255000
1"
#1256000
b1110 0
b101 1
b10 .
b11 /
b1010 (
b1010 -
b1100 $
b1100 *
b101111001001101 %
b101111001001101 +
b111110 )
#1260000
0"
#1265000
b11011010 !
b11011010 2
1"
#1266000
b11011010 #
#1270000
0"
#1275000
1"
#1276000
b110 0
b1010 1
b0 .
b10 /
b1101 (
b1101 -
b101 $
b101 *
b1010101011100110 %
b1010101011100110 +
b111111 )
#1280000
0"
#1285000
b11001010 !
b11001010 2
1"
#1286000
b11001010 #
#1290000
0"
#1295000
1"
#1296000
b10 0
b1111 1
b1 /
b1011 '
b1011 ,
b111 (
b111 -
b11 $
b11 *
b1000011110010 %
b1000011110010 +
b1000000 )
#1300000
0"
#1305000
b1111111 !
b1111111 2
1"
#1306000
b1111111 #
#1310000
0"
#1315000
1"
#1316000
b111 0
b0 1
b1 .
b11 /
b111 '
b111 ,
b1111 (
b1111 -
b1010 $
b1010 *
b11001110000 %
b11001110000 +
b1000001 )
#1320000
0"
#1325000
b110001 !
b110001 2
1"
#1326000
b110001 #
#1330000
0"
#1335000
1"
#1336000
b11 0
b110 1
b0 .
b1 /
b1011 '
b1011 ,
b101 (
b101 -
b11 $
b11 *
b1000111001100011 %
b1000111001100011 +
b1000010 )
#1340000
0"
#1345000
b111111 !
b111111 2
1"
#1346000
b111111 #
#1350000
0"
#1355000
1"
#1356000
b1001 0
b11 1
b1100 '
b1100 ,
b1100 (
b1100 -
b1001000000111001 %
b1001000000111001 +
b1000011 )
#1360000
0"
#1365000
b10010000 !
b10010000 2
1"
#1366000
b10010000 #
#1370000
0"
#1375000
1"
#1376000
b11 0
b1001 1
b1 .
b10 /
b1011 '
b1011 ,
b1101 (
b1101 -
b110 $
b110 *
b11100100110111 %
b11100100110111 +
b1000100 )
#1380000
0"
#1385000
b10010110 !
b10010110 2
1"
#1386000
b10010110 #
#1390000
0"
#1395000
1"
#1396000
b10 0
b0 1
b0 .
b10 /
b1111 '
b1111 ,
b101 $
b101 *
b1101000010100010 %
b1101000010100010 +
b1000101 )
#1400000
0"
#1405000
b11110 !
b11110 2
1"
#1406000
b11110 #
#1410000
0"
#1415000
1"
#1416000
b100 0
b1101 1
b1 .
b10 /
b1110 (
b1110 -
b110 $
b110 *
b101110101001110 %
b101110101001110 +
b1000110 )
#1420000
0"
#1425000
b11110010 !
b11110010 2
1"
#1426000
b11110010 #
#1430000
0"
#1435000
1"
#1436000
b1010 0
b10 1
b1 .
b11 /
b1110 '
b1110 ,
b1010 $
b1010 *
b10011110101000 %
b10011110101000 +
b1000111 )
#1440000
0"
#1445000
b10101000 !
b10101000 2
1"
#1446000
b10101000 #
#1450000
0"
#1455000
1"
#1456000
b1100 0
b0 1
b0 .
b10 /
b1010 '
b1010 ,
b1111 (
b1111 -
b101 $
b101 *
b1111000010101100 %
b1111000010101100 +
b1001000 )
#1460000
0"
#1465000
b1111000 !
b1111000 2
1"
#1466000
b1111000 #
#1470000
0"
#1475000
1"
#1476000
b1011 0
b1010 1
b1000 '
b1000 ,
b110 (
b110 -
b1000101010001011 %
b1000101010001011 +
b1001001 )
#1480000
0"
#1485000
b10010100 !
b10010100 2
1"
#1486000
b10010100 #
#1490000
0"
#1495000
1"
#1496000
b111 0
b1101 1
b1 /
b1111 '
b1111 ,
b1111 (
b1111 -
b11 $
b11 *
b111111111010111 %
b111111111010111 +
b1001010 )
#1500000
0"
#1505000
b100101100 !
b100101100 2
1"
#1506000
b100101100 #
#1510000
0"
#1515000
1"
#1516000
b1100 1
b10 .
b11 /
b1011 '
b1011 ,
b1100 $
b1100 *
b1100011110010010 %
b1100011110010010 +
b1001011 )
#1520000
0"
#1525000
b100000001 !
b100000001 2
1"
#1526000
b100000001 #
#1530000
0"
#1535000
1"
#1536000
b1011 0
b1010 1
b0 .
b10 /
b1110 '
b1110 ,
b1001 (
b1001 -
b101 $
b101 *
b1011101011011011 %
b1011101011011011 +
b1001100 )
#1540000
0"
#1545000
b11110100 !
b11110100 2
1"
#1546000
b11110100 #
#1550000
0"
#1555000
1"
#1556000
b110 0
b10 .
b11 /
b110 '
b110 ,
b110 (
b110 -
b1100 $
b1100 *
b1010011000110111 %
b1010011000110111 +
b1001101 )
#1560000
0"
#1565000
b1100000 !
b1100000 2
1"
#1566000
b1100000 #
#1570000
0"
#1575000
1"
#1576000
b1000 0
b11 1
b1 .
b11 /
b1001 '
b1001 ,
b1011 (
b1011 -
b1010 $
b1010 *
b11100110001111 %
b11100110001111 +
b1001110 )
#1580000
0"
#1585000
b1101001 !
b1101001 2
1"
#1586000
b1101001 #
#1590000
0"
#1595000
1"
#1596000
b101 0
b100 1
b0 .
b11 /
b1000 '
b1000 ,
b1001 (
b1001 -
b1001 $
b1001 *
b100000010010101 %
b100000010010101 +
b1001111 )
#1600000
0"
#1605000
b1001100 !
b1001100 2
1"
#1606000
b1001100 #
#1610000
0"
#1615000
1"
#1616000
b1111 0
b11 1
b1 .
b10 /
b1111 '
b1111 ,
b1111 (
b1111 -
b110 $
b110 *
b1111110100 %
b1111110100 +
b1010000 )
#1620000
0"
#1625000
b100001110 !
b100001110 2
1"
#1626000
b100001110 #
#1630000
0"
#1635000
1"
#1636000
b1010 0
b1000 1
b0 .
b11 /
b1100 (
b1100 -
b1001 $
b1001 *
b1000000101011010 %
b1000000101011010 +
b1010001 )
#1640000
0"
#1645000
b11110110 !
b11110110 2
1"
#1646000
b11110110 #
#1650000
0"
#1655000
1"
#1656000
b10 0
b100 1
b1 .
b11 /
b1001 '
b1001 ,
b111 (
b111 -
b1010 $
b1010 *
b100000100101111 %
b100000100101111 +
b1010010 )
#1660000
0"
#1665000
b101110 !
b101110 2
1"
#1666000
b101110 #
#1670000
0"
#1675000
1"
#1676000
b11 0
b1101 1
b0 .
b1 /
b1110 '
b1110 ,
b1110 (
b1110 -
b11 $
b11 *
b1100011111010011 %
b1100011111010011 +
b1010011 )
#1680000
0"
#1685000
b11100000 !
b11100000 2
1"
#1686000
b11100000 #
#1690000
0"
#1695000
1"
#1696000
b1001 0
b1 1
b110 '
b110 ,
b1000 (
b1000 -
b110001100011001 %
b110001100011001 +
b1010100 )
#1700000
0"
#1705000
b111110 !
b111110 2
1"
#1706000
b111110 #
#1710000
0"
#1715000
1"
#1716000
b10 0
b101 1
b10 .
b11 /
b1110 '
b1110 ,
b1111 (
b1111 -
b1100 $
b1100 *
b101001001010111 %
b101001001010111 +
b1010101 )
#1720000
0"
#1725000
b1100111 !
b1100111 2
1"
#1726000
b1100111 #
#1730000
0"
#1735000
1"
#1736000
b1001 0
b1 1
b0 .
b1 /
b1001 '
b1001 ,
b1110 (
b1110 -
b11 $
b11 *
b1001011100011001 %
b1001011100011001 +
b1010110 )
#1740000
0"
#1745000
b1011111 !
b1011111 2
1"
#1746000
b1011111 #
#1750000
0"
#1755000
1"
#1756000
b1000 0
b1101 1
b10 /
b111 '
b111 ,
b1000 (
b1000 -
b101 $
b101 *
b11110101101000 %
b11110101101000 +
b1010111 )
#1760000
0"
#1765000
b10100000 !
b10100000 2
1"
#1766000
b10100000 #
#1770000
0"
#1775000
1"
#1776000
b1 0
b1001 1
b1 .
b11 /
b1110 '
b1110 ,
b1110 (
b1110 -
b1010 $
b1010 *
b1001010100010010 %
b1001010100010010 +
b1011000 )
#1780000
0"
#1785000
b10001100 !
b10001100 2
1"
#1786000
b10001100 #
#1790000
0"
#1795000
1"
#1796000
b1001 0
b1111 1
b0 .
b11 /
b1101 (
b1101 -
b1001 $
b1001 *
b1111100011001001 %
b1111100011001001 +
b1011001 )
#1800000
0"
#1805000
b101000001 !
b101000001 2
1"
#1806000
b101000001 #
#1810000
0"
#1815000
1"
#1816000
b1010 0
b0 1
b10 /
b111 '
b111 ,
b1000 (
b1000 -
b101 $
b101 *
b10000010001010 %
b10000010001010 +
b1011010 )
#1820000
0"
#1825000
b1000110 !
b1000110 2
1"
#1826000
b1000110 #
#1830000
0"
#1835000
1"
#1836000
b1111 0
b1110 1
b1 .
b10 /
b1101 '
b1101 ,
b1111 (
b1111 -
b110 $
b110 *
b1000111011110101 %
b1000111011110101 +
b1011011 )
#1840000
0"
#1845000
b110010101 !
b110010101 2
1"
#1846000
b110010101 #
#1850000
0"
#1855000
1"
#1856000
b1010 1
b0 .
b11 /
b1010 '
b1010 ,
b1010 (
b1010 -
b1001 $
b1001 *
b1010110110111111 %
b1010110110111111 +
b1011100 )
#1860000
0"
#1865000
b11111010 !
b11111010 2
1"
#1866000
b11111010 #
#1870000
0"
#1875000
1"
#1876000
b1100 1
b1 .
b11 /
b1110 '
b1110 ,
b1010 $
b1010 *
b1100100111111101 %
b1100100111111101 +
b1011101 )
#1880000
0"
#1885000
b101001010 !
b101001010 2
1"
#1886000
b101001010 #
#1890000
0"
#1895000
1"
#1896000
b1010 0
b11 1
b1 .
b10 /
b1101 (
b1101 -
b110 $
b110 *
b1100001110101000 %
b1100001110101000 +
b1011110 )
#1900000
0"
#1905000
b10110011 !
b10110011 2
1"
